Workbook

Sheet Summary
A1: BugReplay — Base and Downside planning summary
A3: Selected case | B3: =Assumptions!B3 -> Base
A4: Cost basis | B4: =Assumptions!B4 -> Planning
A6: Measure | B6: Base | C6: Downside
A7: Annual revenue | B7: =IF(COUNT('Base forecast'!B10:M10)=12,SUM('Base forecast'!B10:M10),"Unknown") -> 42966.417 | C7: =IF(COUNT('Downside forecast'!B10:M10)=12,SUM('Downside forecast'!B10:M10),"Unknown") -> 10901.895
A8: Contribution before hosting | B8: =IF(COUNT('Base forecast'!B15:M15)=12,SUM('Base forecast'!B15:M15),"Unknown") -> 37205.41 | C8: =IF(COUNT('Downside forecast'!B15:M15)=12,SUM('Downside forecast'!B15:M15),"Unknown") -> 4167.1939
A9: Gross profit after hosting | B9: =IF(COUNT('Base forecast'!B18:M18)=12,SUM('Base forecast'!B18:M18),"Unknown") -> 36605.41 | C9: =IF(COUNT('Downside forecast'!B18:M18)=12,SUM('Downside forecast'!B18:M18),"Unknown") -> 2967.1939
A10: Gross margin | B10: =IFERROR(B9/B7,"Unknown") -> 0.85195397 | C10: =IFERROR(C9/C7,"Unknown") -> 0.27217229
A11: Final cash | B11: ='Base forecast'!M26 -> 30405.41 | C11: ='Downside forecast'!M26 -> -17032.806
A12: Closing teams | B12: ='Base forecast'!M8 -> 178.03508 | C12: ='Downside forecast'!M8 -> 39.348899
A13: First negative month | B13: =IF(COUNT('Base forecast'!B26:M26)<>12,"Unknown",IF(SUM('Base forecast'!B27:M27)=0,"None in horizon",INDEX('Base forecast'!B4:M4,1,MATCH(1,'Base forecast'!B27:M27,0)))) -> None in horizon | C13: =IF(COUNT('Downside forecast'!B26:M26)<>12,"Unknown",IF(SUM('Downside forecast'!B27:M27)=0,"None in horizon",INDEX('Downside forecast'!B4:M4,1,MATCH(1,'Downside forecast'!B27:M27,0)))) -> 46447
A16: No paying customers or validated prices. Negative cash is unfunded need, not assumed debt.
A17: Tax, debt, capex and working-capital timing excluded. Month-end liquidity test, not intra-month.

Sheet Assumptions
A1: BugReplay editable planning assumptions — USD
A3: Case selector | B3: Base
A4: Cost basis | B4: Planning
A6: Driver | B6: Base | C6: Downside | D6: Unit / definition
A7: Opening cash | B7: 10000 | C7: 10000 | D7: USD
A8: Opening teams | B8: 0 | C8: 0 | D8: teams
A9: Price per team | B9: 49 | C9: 49 | D9: USD/month
A10: Included investigations | B10: 100 | C10: 100 | D10: runs/team/month
A11: Churn | B11: 0.03 | C11: 0.08 | D11: fraction of opening teams
A12: Utilization | B12: 0.6 | C12: 1 | D12: fraction of allowance
A13: Inference cost | B13: 0.06 | C13: 0.25 | D13: USD/run, commercial
A14: Browser cost | B14: 0.015 | C14: 0.025 | D14: USD/run
A15: Storage cost | B15: 0.005 | C15: 0.01 | D15: USD/run
A16: Payment fee rate | B16: 0.03 | C16: 0.03 | D16: fraction of revenue
A17: Payment fee per team | B17: 0.3 | C17: 0.3 | D17: USD/month
A18: Fixed hosting | B18: 50 | C18: 100 | D18: USD/month
... A22: Contribution target | B22: 0.7 | C22: 0.7 | D22: before hosting
A24: Monthly new teams
A25: Month | B25: Base | C25: Downside
A26: 46327 | B26: 5 | C26: 2
A27: 46357 | B27: 6 | C27: 2
A28: 46388 | B28: 8 | C28: 3
A29: 46419 | B29: 10 | C29: 3
A30: 46447 | B30: 12 | C30: 4
A31: 46478 | B31: 15 | C31: 4
A32: 46508 | B32: 18 | C32: 5
A33: 46539 | B33: 20 | C33: 5
A34: 46569 | B34: 22 | C34: 6
A35: 46600 | B35: 25 | C35: 6
A36: 46631 | B36: 28 | C36: 7
A37: 46661 | B37: 30 | C37: 7
A39: All values are illustrative assumptions. No measured paying customers or validated prices.

Sheet Monthly cash
A1: Selected monthly cash and runway — USD
A2: =Assumptions!B3 -> Base
B4: 46327 | C4: 46357 | D4: 46388 | E4: 46419 | F4: 46447 | G4: 46478 | H4: 46508 | I4: 46539 | J4: 46569 | K4: 46600 | L4: 46631 | M4: 46661
A5: Opening teams | B5: =IF(Assumptions!$B$3="Base",'Base forecast'!B5,'Downside forecast'!B5) -> 0 | C5: =IF(Assumptions!$B$3="Base",'Base forecast'!C5,'Downside forecast'!C5) -> 5 | D5: =IF(Assumptions!$B$3="Base",'Base forecast'!D5,'Downside forecast'!D5) -> 10.85 | E5: =IF(Assumptions!$B$3="Base",'Base forecast'!E5,'Downside forecast'!E5) -> 18.5245 | F5: =IF(Assumptions!$B$3="Base",'Base forecast'!F5,'Downside forecast'!F5) -> 27.968765 | G5: =IF(Assumptions!$B$3="Base",'Base forecast'!G5,'Downside forecast'!G5) -> 39.129702 | H5: =IF(Assumptions!$B$3="Base",'Base forecast'!H5,'Downside forecast'!H5) -> 52.955811 | I5: =IF(Assumptions!$B$3="Base",'Base forecast'!I5,'Downside forecast'!I5) -> 69.367137 | ... M5: =IF(Assumptions!$B$3="Base",'Base forecast'!M5,'Downside forecast'!M5) -> 152.61349
A6: New teams | B6: =IF(Assumptions!$B$3="Base",'Base forecast'!B6,'Downside forecast'!B6) -> 5 | C6: =IF(Assumptions!$B$3="Base",'Base forecast'!C6,'Downside forecast'!C6) -> 6 | D6: =IF(Assumptions!$B$3="Base",'Base forecast'!D6,'Downside forecast'!D6) -> 8 | E6: =IF(Assumptions!$B$3="Base",'Base forecast'!E6,'Downside forecast'!E6) -> 10 | F6: =IF(Assumptions!$B$3="Base",'Base forecast'!F6,'Downside forecast'!F6) -> 12 | G6: =IF(Assumptions!$B$3="Base",'Base forecast'!G6,'Downside forecast'!G6) -> 15 | H6: =IF(Assumptions!$B$3="Base",'Base forecast'!H6,'Downside forecast'!H6) -> 18 | I6: =IF(Assumptions!$B$3="Base",'Base forecast'!I6,'Downside forecast'!I6) -> 20 | ... M6: =IF(Assumptions!$B$3="Base",'Base forecast'!M6,'Downside forecast'!M6) -> 30
A7: Churned teams | B7: =IF(Assumptions!$B$3="Base",'Base forecast'!B7,'Downside forecast'!B7) -> 0 | C7: =IF(Assumptions!$B$3="Base",'Base forecast'!C7,'Downside forecast'!C7) -> 0.15 | D7: =IF(Assumptions!$B$3="Base",'Base forecast'!D7,'Downside forecast'!D7) -> 0.3255 | E7: =IF(Assumptions!$B$3="Base",'Base forecast'!E7,'Downside forecast'!E7) -> 0.555735 | F7: =IF(Assumptions!$B$3="Base",'Base forecast'!F7,'Downside forecast'!F7) -> 0.83906295 | G7: =IF(Assumptions!$B$3="Base",'Base forecast'!G7,'Downside forecast'!G7) -> 1.1738911 | H7: =IF(Assumptions!$B$3="Base",'Base forecast'!H7,'Downside forecast'!H7) -> 1.5886743 | I7: =IF(Assumptions!$B$3="Base",'Base forecast'!I7,'Downside forecast'!I7) -> 2.0810141 | ... M7: =IF(Assumptions!$B$3="Base",'Base forecast'!M7,'Downside forecast'!M7) -> 4.5784046
A8: Closing teams | B8: =IF(Assumptions!$B$3="Base",'Base forecast'!B8,'Downside forecast'!B8) -> 5 | C8: =IF(Assumptions!$B$3="Base",'Base forecast'!C8,'Downside forecast'!C8) -> 10.85 | D8: =IF(Assumptions!$B$3="Base",'Base forecast'!D8,'Downside forecast'!D8) -> 18.5245 | E8: =IF(Assumptions!$B$3="Base",'Base forecast'!E8,'Downside forecast'!E8) -> 27.968765 | F8: =IF(Assumptions!$B$3="Base",'Base forecast'!F8,'Downside forecast'!F8) -> 39.129702 | G8: =IF(Assumptions!$B$3="Base",'Base forecast'!G8,'Downside forecast'!G8) -> 52.955811 | H8: =IF(Assumptions!$B$3="Base",'Base forecast'!H8,'Downside forecast'!H8) -> 69.367137 | I8: =IF(Assumptions!$B$3="Base",'Base forecast'!I8,'Downside forecast'!I8) -> 87.286123 | ... M8: =IF(Assumptions!$B$3="Base",'Base forecast'!M8,'Downside forecast'!M8) -> 178.03508
A9: Investigations | B9: =IF(Assumptions!$B$3="Base",'Base forecast'!B9,'Downside forecast'!B9) -> 300 | C9: =IF(Assumptions!$B$3="Base",'Base forecast'!C9,'Downside forecast'!C9) -> 651 | D9: =IF(Assumptions!$B$3="Base",'Base forecast'!D9,'Downside forecast'!D9) -> 1111.47 | E9: =IF(Assumptions!$B$3="Base",'Base forecast'!E9,'Downside forecast'!E9) -> 1678.1259 | F9: =IF(Assumptions!$B$3="Base",'Base forecast'!F9,'Downside forecast'!F9) -> 2347.7821 | G9: =IF(Assumptions!$B$3="Base",'Base forecast'!G9,'Downside forecast'!G9) -> 3177.3487 | H9: =IF(Assumptions!$B$3="Base",'Base forecast'!H9,'Downside forecast'!H9) -> 4162.0282 | I9: =IF(Assumptions!$B$3="Base",'Base forecast'!I9,'Downside forecast'!I9) -> 5237.1674 | ... M9: =IF(Assumptions!$B$3="Base",'Base forecast'!M9,'Downside forecast'!M9) -> 10682.105
A10: Revenue | B10: =IF(Assumptions!$B$3="Base",'Base forecast'!B10,'Downside forecast'!B10) -> 245 | C10: =IF(Assumptions!$B$3="Base",'Base forecast'!C10,'Downside forecast'!C10) -> 531.65 | D10: =IF(Assumptions!$B$3="Base",'Base forecast'!D10,'Downside forecast'!D10) -> 907.7005 | E10: =IF(Assumptions!$B$3="Base",'Base forecast'!E10,'Downside forecast'!E10) -> 1370.4695 | F10: =IF(Assumptions!$B$3="Base",'Base forecast'!F10,'Downside forecast'!F10) -> 1917.3554 | G10: =IF(Assumptions!$B$3="Base",'Base forecast'!G10,'Downside forecast'!G10) -> 2594.8347 | H10: =IF(Assumptions!$B$3="Base",'Base forecast'!H10,'Downside forecast'!H10) -> 3398.9897 | I10: =IF(Assumptions!$B$3="Base",'Base forecast'!I10,'Downside forecast'!I10) -> 4277.02 | ... M10: =IF(Assumptions!$B$3="Base",'Base forecast'!M10,'Downside forecast'!M10) -> 8723.7191
A11: Run cost per investigation | B11: =IF(Assumptions!$B$3="Base",'Base forecast'!B11,'Downside forecast'!B11) -> 0.08 | C11: =IF(Assumptions!$B$3="Base",'Base forecast'!C11,'Downside forecast'!C11) -> 0.08 | D11: =IF(Assumptions!$B$3="Base",'Base forecast'!D11,'Downside forecast'!D11) -> 0.08 | E11: =IF(Assumptions!$B$3="Base",'Base forecast'!E11,'Downside forecast'!E11) -> 0.08 | F11: =IF(Assumptions!$B$3="Base",'Base forecast'!F11,'Downside forecast'!F11) -> 0.08 | G11: =IF(Assumptions!$B$3="Base",'Base forecast'!G11,'Downside forecast'!G11) -> 0.08 | H11: =IF(Assumptions!$B$3="Base",'Base forecast'!H11,'Downside forecast'!H11) -> 0.08 | I11: =IF(Assumptions!$B$3="Base",'Base forecast'!I11,'Downside forecast'!I11) -> 0.08 | ... M11: =IF(Assumptions!$B$3="Base",'Base forecast'!M11,'Downside forecast'!M11) -> 0.08
A12: Investigation variable cost | B12: =IF(Assumptions!$B$3="Base",'Base forecast'!B12,'Downside forecast'!B12) -> 24 | C12: =IF(Assumptions!$B$3="Base",'Base forecast'!C12,'Downside forecast'!C12) -> 52.08 | D12: =IF(Assumptions!$B$3="Base",'Base forecast'!D12,'Downside forecast'!D12) -> 88.9176 | E12: =IF(Assumptions!$B$3="Base",'Base forecast'!E12,'Downside forecast'!E12) -> 134.25007 | F12: =IF(Assumptions!$B$3="Base",'Base forecast'!F12,'Downside forecast'!F12) -> 187.82257 | G12: =IF(Assumptions!$B$3="Base",'Base forecast'!G12,'Downside forecast'!G12) -> 254.18789 | H12: =IF(Assumptions!$B$3="Base",'Base forecast'!H12,'Downside forecast'!H12) -> 332.96226 | I12: =IF(Assumptions!$B$3="Base",'Base forecast'!I12,'Downside forecast'!I12) -> 418.97339 | ... M12: =IF(Assumptions!$B$3="Base",'Base forecast'!M12,'Downside forecast'!M12) -> 854.5684
A13: Payment fees | B13: =IF(Assumptions!$B$3="Base",'Base forecast'!B13,'Downside forecast'!B13) -> 8.85 | C13: =IF(Assumptions!$B$3="Base",'Base forecast'!C13,'Downside forecast'!C13) -> 19.2045 | D13: =IF(Assumptions!$B$3="Base",'Base forecast'!D13,'Downside forecast'!D13) -> 32.788365 | E13: =IF(Assumptions!$B$3="Base",'Base forecast'!E13,'Downside forecast'!E13) -> 49.504714 | F13: =IF(Assumptions!$B$3="Base",'Base forecast'!F13,'Downside forecast'!F13) -> 69.259573 | G13: =IF(Assumptions!$B$3="Base",'Base forecast'!G13,'Downside forecast'!G13) -> 93.731785 | H13: =IF(Assumptions!$B$3="Base",'Base forecast'!H13,'Downside forecast'!H13) -> 122.77983 | I13: =IF(Assumptions!$B$3="Base",'Base forecast'!I13,'Downside forecast'!I13) -> 154.49644 | ... M13: =IF(Assumptions!$B$3="Base",'Base forecast'!M13,'Downside forecast'!M13) -> 315.1221
A14: Total variable cost | B14: =IF(Assumptions!$B$3="Base",'Base forecast'!B14,'Downside forecast'!B14) -> 32.85 | C14: =IF(Assumptions!$B$3="Base",'Base forecast'!C14,'Downside forecast'!C14) -> 71.2845 | D14: =IF(Assumptions!$B$3="Base",'Base forecast'!D14,'Downside forecast'!D14) -> 121.70597 | E14: =IF(Assumptions!$B$3="Base",'Base forecast'!E14,'Downside forecast'!E14) -> 183.75479 | F14: =IF(Assumptions!$B$3="Base",'Base forecast'!F14,'Downside forecast'!F14) -> 257.08214 | G14: =IF(Assumptions!$B$3="Base",'Base forecast'!G14,'Downside forecast'!G14) -> 347.91968 | H14: =IF(Assumptions!$B$3="Base",'Base forecast'!H14,'Downside forecast'!H14) -> 455.74209 | I14: =IF(Assumptions!$B$3="Base",'Base forecast'!I14,'Downside forecast'!I14) -> 573.46983 | ... M14: =IF(Assumptions!$B$3="Base",'Base forecast'!M14,'Downside forecast'!M14) -> 1169.6905
A15: Contribution before hosting | B15: =IF(Assumptions!$B$3="Base",'Base forecast'!B15,'Downside forecast'!B15) -> 212.15 | C15: =IF(Assumptions!$B$3="Base",'Base forecast'!C15,'Downside forecast'!C15) -> 460.3655 | D15: =IF(Assumptions!$B$3="Base",'Base forecast'!D15,'Downside forecast'!D15) -> 785.99454 | E15: =IF(Assumptions!$B$3="Base",'Base forecast'!E15,'Downside forecast'!E15) -> 1186.7147 | F15: =IF(Assumptions!$B$3="Base",'Base forecast'!F15,'Downside forecast'!F15) -> 1660.2733 | G15: =IF(Assumptions!$B$3="Base",'Base forecast'!G15,'Downside forecast'!G15) -> 2246.9151 | H15: =IF(Assumptions!$B$3="Base",'Base forecast'!H15,'Downside forecast'!H15) -> 2943.2476 | I15: =IF(Assumptions!$B$3="Base",'Base forecast'!I15,'Downside forecast'!I15) -> 3703.5502 | ... M15: =IF(Assumptions!$B$3="Base",'Base forecast'!M15,'Downside forecast'!M15) -> 7554.0286
A16: Contribution margin before hosting | B16: =IF(Assumptions!$B$3="Base",'Base forecast'!B16,'Downside forecast'!B16) -> 0.86591837 | C16: =IF(Assumptions!$B$3="Base",'Base forecast'!C16,'Downside forecast'!C16) -> 0.86591837 | D16: =IF(Assumptions!$B$3="Base",'Base forecast'!D16,'Downside forecast'!D16) -> 0.86591837 | E16: =IF(Assumptions!$B$3="Base",'Base forecast'!E16,'Downside forecast'!E16) -> 0.86591837 | F16: =IF(Assumptions!$B$3="Base",'Base forecast'!F16,'Downside forecast'!F16) -> 0.86591837 | G16: =IF(Assumptions!$B$3="Base",'Base forecast'!G16,'Downside forecast'!G16) -> 0.86591837 | H16: =IF(Assumptions!$B$3="Base",'Base forecast'!H16,'Downside forecast'!H16) -> 0.86591837 | I16: =IF(Assumptions!$B$3="Base",'Base forecast'!I16,'Downside forecast'!I16) -> 0.86591837 | ... M16: =IF(Assumptions!$B$3="Base",'Base forecast'!M16,'Downside forecast'!M16) -> 0.86591837
... A28: Unfunded deficit | B28: =IF(Assumptions!$B$3="Base",'Base forecast'!B28,'Downside forecast'!B28) -> 0 | C28: =IF(Assumptions!$B$3="Base",'Base forecast'!C28,'Downside forecast'!C28) -> 0 | D28: =IF(Assumptions!$B$3="Base",'Base forecast'!D28,'Downside forecast'!D28) -> 0 | E28: =IF(Assumptions!$B$3="Base",'Base forecast'!E28,'Downside forecast'!E28) -> 0 | F28: =IF(Assumptions!$B$3="Base",'Base forecast'!F28,'Downside forecast'!F28) -> 0 | G28: =IF(Assumptions!$B$3="Base",'Base forecast'!G28,'Downside forecast'!G28) -> 0 | H28: =IF(Assumptions!$B$3="Base",'Base forecast'!H28,'Downside forecast'!H28) -> 0 | I28: =IF(Assumptions!$B$3="Base",'Base forecast'!I28,'Downside forecast'!I28) -> 0 | ... M28: =IF(Assumptions!$B$3="Base",'Base forecast'!M28,'Downside forecast'!M28) -> 0
A31: First negative cash | B31: =IF(COUNT(B26:M26)<>12,"Unknown",IF(SUM(B27:M27)=0,"None in horizon",INDEX(B4:M4,1,MATCH(1,B27:M27,0)))) -> None in horizon

Sheet Price-cost sensitivity
A1: Contribution before hosting — price and all-run cost
A3: Selected price | B3: =IF(Assumptions!B3="Base",Assumptions!B9,Assumptions!C9) -> 49
A4: Included runs | B4: =IF(Assumptions!B3="Base",Assumptions!B10,Assumptions!C10) -> 100
A5: Fee rate | B5: =IF(Assumptions!B3="Base",Assumptions!B16,Assumptions!C16) -> 0.03
A6: Fee / team | B6: =IF(Assumptions!B3="Base",Assumptions!B17,Assumptions!C17) -> 0.3
A7: Target contribution | B7: =IF(Assumptions!B3="Base",Assumptions!B22,Assumptions!C22) -> 0.7
A8: Selected assumed run cost | B8: =IF(Assumptions!B3="Base",SUM(Assumptions!B13:B15),SUM(Assumptions!C13:C15)) -> 0.08
A10: Full-allowance contribution margin | B10: =(B3*(1-B5)-B6-B4*B8)/B3 -> 0.80061224
A11: Max run cost at target | B11: =(B3*(1-B7-B5)-B6)/B4 -> 0.1293
A12: Min price at target | B12: =(B4*B8+B6)/(1-B7-B5) -> 30.740741
A13: Max whole allowance at target | B13: =MAX(0,INT((B3*(1-B7-B5)-B6)/B8)) -> 161
A16: Run cost / price | B16: 29 | C16: 49 | D16: 79 | E16: 106.66667 | F16: 129
A17: 0.08 | B17: =(B$16*(1-$B$5)-$B$6-$B$4*$A17)/B$16 -> 0.6837931 | C17: =(C$16*(1-$B$5)-$B$6-$B$4*$A17)/C$16 -> 0.80061224 | D17: =(D$16*(1-$B$5)-$B$6-$B$4*$A17)/D$16 -> 0.86493671 | E17: =(E$16*(1-$B$5)-$B$6-$B$4*$A17)/E$16 -> 0.8921875 | F17: =(F$16*(1-$B$5)-$B$6-$B$4*$A17)/F$16 -> 0.90565891
A18: 0.1293 | B18: =(B$16*(1-$B$5)-$B$6-$B$4*$A18)/B$16 -> 0.5137931 | C18: =(C$16*(1-$B$5)-$B$6-$B$4*$A18)/C$16 -> 0.7 | D18: =(D$16*(1-$B$5)-$B$6-$B$4*$A18)/D$16 -> 0.80253165 | E18: =(E$16*(1-$B$5)-$B$6-$B$4*$A18)/E$16 -> 0.84596875 | F18: =(F$16*(1-$B$5)-$B$6-$B$4*$A18)/F$16 -> 0.86744186
A19: 0.285 | B19: =(B$16*(1-$B$5)-$B$6-$B$4*$A19)/B$16 -> -0.023103448 | C19: =(C$16*(1-$B$5)-$B$6-$B$4*$A19)/C$16 -> 0.3822449 | D19: =(D$16*(1-$B$5)-$B$6-$B$4*$A19)/D$16 -> 0.60544304 | E19: =(E$16*(1-$B$5)-$B$6-$B$4*$A19)/E$16 -> 0.7 | F19: =(F$16*(1-$B$5)-$B$6-$B$4*$A19)/F$16 -> 0.74674419
A20: 0.5 | B20: =(B$16*(1-$B$5)-$B$6-$B$4*$A20)/B$16 -> -0.76448276 | C20: =(C$16*(1-$B$5)-$B$6-$B$4*$A20)/C$16 -> -0.056530612 | D20: =(D$16*(1-$B$5)-$B$6-$B$4*$A20)/D$16 -> 0.33329114 | E20: =(E$16*(1-$B$5)-$B$6-$B$4*$A20)/E$16 -> 0.4984375 | F20: =(F$16*(1-$B$5)-$B$6-$B$4*$A20)/F$16 -> 0.58007752
A23: Decision: $49 / 100 is a hypothesis. Measure every paid run and reprice / reduce allowance if the target fails.
A24: Sensitivity holds customers unchanged. No price elasticity or technical acceptance is claimed.

Sheet Assumptions vs actuals
A1: Actual paid attempts — empty; Unknown is not zero
A3: Expected paid attempts (independent provider/execution ledger)
A4: Entered attempts | B4: =SUM(L13:L212) -> 0
A5: Invalid attempts | B5: =SUM(M13:M212) -> 0
A6: Missing attempts | B6: =IF(ISNUMBER(B3),MAX(0,B3-B4),"Unknown") -> Unknown
A7: Actual all-run commercial cost | B7: =IF(OR(NOT(ISNUMBER(B3)),B3<>B4,B4=0,B5>0),"Unknown",SUM(F13:F212)/B4) -> Unknown
A8: Actual status | B8: =IF(ISNUMBER(B7),"Measured","Unknown") -> Unknown
A9: Inference cost basis | B9: =Assumptions!B4 -> Planning
A12: Run ID | B12: Date (UTC) | C12: Outcome | D12: Input tokens | E12: Output tokens | F12: Commercial total cost USD | G12: Duration seconds | H12: Git SHA | I12: Trace link | J12: Cost source | K12: Duplicate ID count | L12: Entered row | M12: Invalid row
K13: =IF(COUNTA(A13:J13)=0,0,IF(A13="",0,COUNTIF($A$13:$A$212,A13))) -> 0 | L13: =IF(COUNTA(A13:J13)=0,0,1) -> 0 | M13: =IF(L13=0,0,IF(OR(A13="",NOT(ISNUMBER(B13)),C13="",NOT(ISNUMBER(F13)),F13<0,J13="",K13<>1),1,0)) -> 0
K14: =IF(COUNTA(A14:J14)=0,0,IF(A14="",0,COUNTIF($A$13:$A$212,A14))) -> 0 | L14: =IF(COUNTA(A14:J14)=0,0,1) -> 0 | M14: =IF(L14=0,0,IF(OR(A14="",NOT(ISNUMBER(B14)),C14="",NOT(ISNUMBER(F14)),F14<0,J14="",K14<>1),1,0)) -> 0
K15: =IF(COUNTA(A15:J15)=0,0,IF(A15="",0,COUNTIF($A$13:$A$212,A15))) -> 0 | L15: =IF(COUNTA(A15:J15)=0,0,1) -> 0 | M15: =IF(L15=0,0,IF(OR(A15="",NOT(ISNUMBER(B15)),C15="",NOT(ISNUMBER(F15)),F15<0,J15="",K15<>1),1,0)) -> 0
K16: =IF(COUNTA(A16:J16)=0,0,IF(A16="",0,COUNTIF($A$13:$A$212,A16))) -> 0 | L16: =IF(COUNTA(A16:J16)=0,0,1) -> 0 | M16: =IF(L16=0,0,IF(OR(A16="",NOT(ISNUMBER(B16)),C16="",NOT(ISNUMBER(F16)),F16<0,J16="",K16<>1),1,0)) -> 0
K17: =IF(COUNTA(A17:J17)=0,0,IF(A17="",0,COUNTIF($A$13:$A$212,A17))) -> 0 | L17: =IF(COUNTA(A17:J17)=0,0,1) -> 0 | M17: =IF(L17=0,0,IF(OR(A17="",NOT(ISNUMBER(B17)),C17="",NOT(ISNUMBER(F17)),F17<0,J17="",K17<>1),1,0)) -> 0
K18: =IF(COUNTA(A18:J18)=0,0,IF(A18="",0,COUNTIF($A$13:$A$212,A18))) -> 0 | L18: =IF(COUNTA(A18:J18)=0,0,1) -> 0 | M18: =IF(L18=0,0,IF(OR(A18="",NOT(ISNUMBER(B18)),C18="",NOT(ISNUMBER(F18)),F18<0,J18="",K18<>1),1,0)) -> 0
K19: =IF(COUNTA(A19:J19)=0,0,IF(A19="",0,COUNTIF($A$13:$A$212,A19))) -> 0 | L19: =IF(COUNTA(A19:J19)=0,0,1) -> 0 | M19: =IF(L19=0,0,IF(OR(A19="",NOT(ISNUMBER(B19)),C19="",NOT(ISNUMBER(F19)),F19<0,J19="",K19<>1),1,0)) -> 0
K20: =IF(COUNTA(A20:J20)=0,0,IF(A20="",0,COUNTIF($A$13:$A$212,A20))) -> 0 | L20: =IF(COUNTA(A20:J20)=0,0,1) -> 0 | M20: =IF(L20=0,0,IF(OR(A20="",NOT(ISNUMBER(B20)),C20="",NOT(ISNUMBER(F20)),F20<0,J20="",K20<>1),1,0)) -> 0
K21: =IF(COUNTA(A21:J21)=0,0,IF(A21="",0,COUNTIF($A$13:$A$212,A21))) -> 0 | L21: =IF(COUNTA(A21:J21)=0,0,1) -> 0 | M21: =IF(L21=0,0,IF(OR(A21="",NOT(ISNUMBER(B21)),C21="",NOT(ISNUMBER(F21)),F21<0,J21="",K21<>1),1,0)) -> 0
K22: =IF(COUNTA(A22:J22)=0,0,IF(A22="",0,COUNTIF($A$13:$A$212,A22))) -> 0 | L22: =IF(COUNTA(A22:J22)=0,0,1) -> 0 | M22: =IF(L22=0,0,IF(OR(A22="",NOT(ISNUMBER(B22)),C22="",NOT(ISNUMBER(F22)),F22<0,J22="",K22<>1),1,0)) -> 0
K23: =IF(COUNTA(A23:J23)=0,0,IF(A23="",0,COUNTIF($A$13:$A$212,A23))) -> 0 | L23: =IF(COUNTA(A23:J23)=0,0,1) -> 0 | M23: =IF(L23=0,0,IF(OR(A23="",NOT(ISNUMBER(B23)),C23="",NOT(ISNUMBER(F23)),F23<0,J23="",K23<>1),1,0)) -> 0
K24: =IF(COUNTA(A24:J24)=0,0,IF(A24="",0,COUNTIF($A$13:$A$212,A24))) -> 0 | L24: =IF(COUNTA(A24:J24)=0,0,1) -> 0 | M24: =IF(L24=0,0,IF(OR(A24="",NOT(ISNUMBER(B24)),C24="",NOT(ISNUMBER(F24)),F24<0,J24="",K24<>1),1,0)) -> 0
... K212: =IF(COUNTA(A212:J212)=0,0,IF(A212="",0,COUNTIF($A$13:$A$212,A212))) -> 0 | L212: =IF(COUNTA(A212:J212)=0,0,1) -> 0 | M212: =IF(L212=0,0,IF(OR(A212="",NOT(ISNUMBER(B212)),C212="",NOT(ISNUMBER(F212)),F212<0,J212="",K212<>1),1,0)) -> 0
A215: Include every paid attempt, including failed/cancelled runs. Cost includes all inference calls, browser and storage, before credits.
A216: Verified commercial cost source is mandatory, including explicit zero. Token counts are not dollar cost evidence.
A217: Entirely missing attempts require an independent expected count. No completeness claim is made while B3 is empty.
A218: Blank optional metadata is retained for evidence review; cost validation requires ID, date, outcome, commercial cost and source.

Sheet Base forecast
A1: Base forecast — all assumptions, USD
B4: 46327 | C4: 46357 | D4: 46388 | E4: 46419 | F4: 46447 | G4: 46478 | H4: 46508 | I4: 46539 | J4: 46569 | K4: 46600 | L4: 46631 | M4: 46661
A5: Opening teams | B5: =Assumptions!$B$8 -> 0 | C5: =B8 -> 5 | D5: =C8 -> 10.85 | E5: =D8 -> 18.5245 | F5: =E8 -> 27.968765 | G5: =F8 -> 39.129702 | H5: =G8 -> 52.955811 | I5: =H8 -> 69.367137 | J5: =I8 -> 87.286123 | ... M5: =L8 -> 152.61349
A6: New teams | B6: =Assumptions!B26 -> 5 | C6: =Assumptions!B27 -> 6 | D6: =Assumptions!B28 -> 8 | E6: =Assumptions!B29 -> 10 | F6: =Assumptions!B30 -> 12 | G6: =Assumptions!B31 -> 15 | H6: =Assumptions!B32 -> 18 | I6: =Assumptions!B33 -> 20 | J6: =Assumptions!B34 -> 22 | K6: =Assumptions!B35 -> 25 | L6: =Assumptions!B36 -> 28 | M6: =Assumptions!B37 -> 30
A7: Churned teams | B7: =B5*Assumptions!$B$11 -> 0 | C7: =C5*Assumptions!$B$11 -> 0.15 | D7: =D5*Assumptions!$B$11 -> 0.3255 | E7: =E5*Assumptions!$B$11 -> 0.555735 | F7: =F5*Assumptions!$B$11 -> 0.83906295 | G7: =G5*Assumptions!$B$11 -> 1.1738911 | H7: =H5*Assumptions!$B$11 -> 1.5886743 | I7: =I5*Assumptions!$B$11 -> 2.0810141 | ... M7: =M5*Assumptions!$B$11 -> 4.5784046
A8: Closing teams | B8: =B5-B7+B6 -> 5 | C8: =C5-C7+C6 -> 10.85 | D8: =D5-D7+D6 -> 18.5245 | E8: =E5-E7+E6 -> 27.968765 | F8: =F5-F7+F6 -> 39.129702 | G8: =G5-G7+G6 -> 52.955811 | H8: =H5-H7+H6 -> 69.367137 | I8: =I5-I7+I6 -> 87.286123 | ... M8: =M5-M7+M6 -> 178.03508
A9: Investigations | B9: =B8*Assumptions!$B$10*Assumptions!$B$12 -> 300 | C9: =C8*Assumptions!$B$10*Assumptions!$B$12 -> 651 | D9: =D8*Assumptions!$B$10*Assumptions!$B$12 -> 1111.47 | E9: =E8*Assumptions!$B$10*Assumptions!$B$12 -> 1678.1259 | F9: =F8*Assumptions!$B$10*Assumptions!$B$12 -> 2347.7821 | G9: =G8*Assumptions!$B$10*Assumptions!$B$12 -> 3177.3487 | H9: =H8*Assumptions!$B$10*Assumptions!$B$12 -> 4162.0282 | I9: =I8*Assumptions!$B$10*Assumptions!$B$12 -> 5237.1674 | ... M9: =M8*Assumptions!$B$10*Assumptions!$B$12 -> 10682.105
A10: Revenue | B10: =B8*Assumptions!$B$9 -> 245 | C10: =C8*Assumptions!$B$9 -> 531.65 | D10: =D8*Assumptions!$B$9 -> 907.7005 | E10: =E8*Assumptions!$B$9 -> 1370.4695 | F10: =F8*Assumptions!$B$9 -> 1917.3554 | G10: =G8*Assumptions!$B$9 -> 2594.8347 | H10: =H8*Assumptions!$B$9 -> 3398.9897 | I10: =I8*Assumptions!$B$9 -> 4277.02 | ... M10: =M8*Assumptions!$B$9 -> 8723.7191
A11: Run cost per investigation | B11: =IF(Assumptions!$B$4="Planning",SUM(Assumptions!$B$13,Assumptions!$B$14,Assumptions!$B$15),'Assumptions vs actuals'!$B$7) -> 0.08 | C11: =IF(Assumptions!$B$4="Planning",SUM(Assumptions!$B$13,Assumptions!$B$14,Assumptions!$B$15),'Assumptions vs actuals'!$B$7) -> 0.08 | D11: =IF(Assumptions!$B$4="Planning",SUM(Assumptions!$B$13,Assumptions!$B$14,Assumptions!$B$15),'Assumptions vs actuals'!$B$7) -> 0.08 | E11: =IF(Assumptions!$B$4="Planning",SUM(Assumptions!$B$13,Assumptions!$B$14,Assumptions!$B$15),'Assumptions vs actuals'!$B$7) -> 0.08 | F11: =IF(Assumptions!$B$4="Planning",SUM(Assumptions!$B$13,Assumptions!$B$14,Assumptions!$B$15),'Assumptions vs actuals'!$B$7) -> 0.08 | G11: =IF(Assumptions!$B$4="Planning",SUM(Assumptions!$B$13,Assumptions!$B$14,Assumptions!$B$15),'Assumptions vs actuals'!$B$7) -> 0.08 | H11: =IF(Assumptions!$B$4="Planning",SUM(Assumptions!$B$13,Assumptions!$B$14,Assumptions!$B$15),'Assumptions vs actuals'!$B$7) -> 0.08 | I11: =IF(Assumptions!$B$4="Planning",SUM(Assumptions!$B$13,Assumptions!$B$14,Assumptions!$B$15),'Assumptions vs actuals'!$B$7) -> 0.08 | ... M11: =IF(Assumptions!$B$4="Planning",SUM(Assumptions!$B$13,Assumptions!$B$14,Assumptions!$B$15),'Assumptions vs actuals'!$B$7) -> 0.08
A12: Investigation variable cost | B12: =IF(ISNUMBER(B11),B9*B11,"Unknown") -> 24 | C12: =IF(ISNUMBER(C11),C9*C11,"Unknown") -> 52.08 | D12: =IF(ISNUMBER(D11),D9*D11,"Unknown") -> 88.9176 | E12: =IF(ISNUMBER(E11),E9*E11,"Unknown") -> 134.25007 | F12: =IF(ISNUMBER(F11),F9*F11,"Unknown") -> 187.82257 | G12: =IF(ISNUMBER(G11),G9*G11,"Unknown") -> 254.18789 | H12: =IF(ISNUMBER(H11),H9*H11,"Unknown") -> 332.96226 | I12: =IF(ISNUMBER(I11),I9*I11,"Unknown") -> 418.97339 | ... M12: =IF(ISNUMBER(M11),M9*M11,"Unknown") -> 854.5684
A13: Payment fees | B13: =B10*Assumptions!$B$16+B8*Assumptions!$B$17 -> 8.85 | C13: =C10*Assumptions!$B$16+C8*Assumptions!$B$17 -> 19.2045 | D13: =D10*Assumptions!$B$16+D8*Assumptions!$B$17 -> 32.788365 | E13: =E10*Assumptions!$B$16+E8*Assumptions!$B$17 -> 49.504714 | F13: =F10*Assumptions!$B$16+F8*Assumptions!$B$17 -> 69.259573 | G13: =G10*Assumptions!$B$16+G8*Assumptions!$B$17 -> 93.731785 | H13: =H10*Assumptions!$B$16+H8*Assumptions!$B$17 -> 122.77983 | I13: =I10*Assumptions!$B$16+I8*Assumptions!$B$17 -> 154.49644 | ... M13: =M10*Assumptions!$B$16+M8*Assumptions!$B$17 -> 315.1221
A14: Total variable cost | B14: =IF(ISNUMBER(B12),B12+B13,"Unknown") -> 32.85 | C14: =IF(ISNUMBER(C12),C12+C13,"Unknown") -> 71.2845 | D14: =IF(ISNUMBER(D12),D12+D13,"Unknown") -> 121.70597 | E14: =IF(ISNUMBER(E12),E12+E13,"Unknown") -> 183.75479 | F14: =IF(ISNUMBER(F12),F12+F13,"Unknown") -> 257.08214 | G14: =IF(ISNUMBER(G12),G12+G13,"Unknown") -> 347.91968 | H14: =IF(ISNUMBER(H12),H12+H13,"Unknown") -> 455.74209 | I14: =IF(ISNUMBER(I12),I12+I13,"Unknown") -> 573.46983 | ... M14: =IF(ISNUMBER(M12),M12+M13,"Unknown") -> 1169.6905
A15: Contribution before hosting | B15: =IF(ISNUMBER(B14),B10-B14,"Unknown") -> 212.15 | C15: =IF(ISNUMBER(C14),C10-C14,"Unknown") -> 460.3655 | D15: =IF(ISNUMBER(D14),D10-D14,"Unknown") -> 785.99454 | E15: =IF(ISNUMBER(E14),E10-E14,"Unknown") -> 1186.7147 | F15: =IF(ISNUMBER(F14),F10-F14,"Unknown") -> 1660.2733 | G15: =IF(ISNUMBER(G14),G10-G14,"Unknown") -> 2246.9151 | H15: =IF(ISNUMBER(H14),H10-H14,"Unknown") -> 2943.2476 | I15: =IF(ISNUMBER(I14),I10-I14,"Unknown") -> 3703.5502 | ... M15: =IF(ISNUMBER(M14),M10-M14,"Unknown") -> 7554.0286
A16: Contribution margin before hosting | B16: =IFERROR(B15/B10,"Unknown") -> 0.86591837 | C16: =IFERROR(C15/C10,"Unknown") -> 0.86591837 | D16: =IFERROR(D15/D10,"Unknown") -> 0.86591837 | E16: =IFERROR(E15/E10,"Unknown") -> 0.86591837 | F16: =IFERROR(F15/F10,"Unknown") -> 0.86591837 | G16: =IFERROR(G15/G10,"Unknown") -> 0.86591837 | H16: =IFERROR(H15/H10,"Unknown") -> 0.86591837 | I16: =IFERROR(I15/I10,"Unknown") -> 0.86591837 | ... M16: =IFERROR(M15/M10,"Unknown") -> 0.86591837
A17: Fixed hosting | B17: =Assumptions!$B$18 -> 50 | C17: =Assumptions!$B$18 -> 50 | D17: =Assumptions!$B$18 -> 50 | E17: =Assumptions!$B$18 -> 50 | F17: =Assumptions!$B$18 -> 50 | G17: =Assumptions!$B$18 -> 50 | H17: =Assumptions!$B$18 -> 50 | I17: =Assumptions!$B$18 -> 50 | ... M17: =Assumptions!$B$18 -> 50
A18: Gross profit | B18: =IF(ISNUMBER(B15),B15-B17,"Unknown") -> 162.15 | C18: =IF(ISNUMBER(C15),C15-C17,"Unknown") -> 410.3655 | D18: =IF(ISNUMBER(D15),D15-D17,"Unknown") -> 735.99454 | E18: =IF(ISNUMBER(E15),E15-E17,"Unknown") -> 1136.7147 | F18: =IF(ISNUMBER(F15),F15-F17,"Unknown") -> 1610.2733 | G18: =IF(ISNUMBER(G15),G15-G17,"Unknown") -> 2196.9151 | H18: =IF(ISNUMBER(H15),H15-H17,"Unknown") -> 2893.2476 | I18: =IF(ISNUMBER(I15),I15-I17,"Unknown") -> 3653.5502 | ... M18: =IF(ISNUMBER(M15),M15-M17,"Unknown") -> 7504.0286
A19: Gross margin | B19: =IFERROR(B18/B10,"Unknown") -> 0.66183673 | C19: =IFERROR(C18/C10,"Unknown") -> 0.77187153 | D19: =IFERROR(D18/D10,"Unknown") -> 0.81083412 | E19: =IFERROR(E18/E10,"Unknown") -> 0.82943452 | F19: =IFERROR(F18/F10,"Unknown") -> 0.83984078 | G19: =IFERROR(G18/G10,"Unknown") -> 0.84664932 | H19: =IFERROR(H18/H10,"Unknown") -> 0.85120811 | I19: =IFERROR(I18/I10,"Unknown") -> 0.85422798 | ... M19: =IFERROR(M18/M10,"Unknown") -> 0.86018687
A20: Founder/contractor cash pay | B20: =Assumptions!$B$19 -> 1000 | C20: =Assumptions!$B$19 -> 1000 | D20: =Assumptions!$B$19 -> 1000 | E20: =Assumptions!$B$19 -> 1000 | F20: =Assumptions!$B$19 -> 1000 | G20: =Assumptions!$B$19 -> 1000 | H20: =Assumptions!$B$19 -> 1000 | I20: =Assumptions!$B$19 -> 1000 | ... M20: =Assumptions!$B$19 -> 1000
A21: Marketing | B21: =Assumptions!$B$20 -> 200 | C21: =Assumptions!$B$20 -> 200 | D21: =Assumptions!$B$20 -> 200 | E21: =Assumptions!$B$20 -> 200 | F21: =Assumptions!$B$20 -> 200 | G21: =Assumptions!$B$20 -> 200 | H21: =Assumptions!$B$20 -> 200 | I21: =Assumptions!$B$20 -> 200 | ... M21: =Assumptions!$B$20 -> 200
A22: Other operating spend | B22: =Assumptions!$B$21 -> 150 | C22: =Assumptions!$B$21 -> 150 | D22: =Assumptions!$B$21 -> 150 | E22: =Assumptions!$B$21 -> 150 | F22: =Assumptions!$B$21 -> 150 | G22: =Assumptions!$B$21 -> 150 | H22: =Assumptions!$B$21 -> 150 | I22: =Assumptions!$B$21 -> 150 | ... M22: =Assumptions!$B$21 -> 150
A23: Total operating spend | B23: =SUM(B20:B22) -> 1350 | C23: =SUM(C20:C22) -> 1350 | D23: =SUM(D20:D22) -> 1350 | E23: =SUM(E20:E22) -> 1350 | F23: =SUM(F20:F22) -> 1350 | G23: =SUM(G20:G22) -> 1350 | H23: =SUM(H20:H22) -> 1350 | I23: =SUM(I20:I22) -> 1350 | ... M23: =SUM(M20:M22) -> 1350
A24: Operating cash flow | B24: =IF(ISNUMBER(B18),B18-B23,"Unknown") -> -1187.85 | C24: =IF(ISNUMBER(C18),C18-C23,"Unknown") -> -939.6345 | D24: =IF(ISNUMBER(D18),D18-D23,"Unknown") -> -614.00546 | E24: =IF(ISNUMBER(E18),E18-E23,"Unknown") -> -213.2853 | F24: =IF(ISNUMBER(F18),F18-F23,"Unknown") -> 260.27326 | G24: =IF(ISNUMBER(G18),G18-G23,"Unknown") -> 846.91506 | H24: =IF(ISNUMBER(H18),H18-H23,"Unknown") -> 1543.2476 | I24: =IF(ISNUMBER(I18),I18-I23,"Unknown") -> 2303.5502 | ... M24: =IF(ISNUMBER(M18),M18-M23,"Unknown") -> 6154.0286
A25: Opening cash | B25: =Assumptions!$B$7 -> 10000 | C25: =B26 -> 8812.15 | D25: =C26 -> 7872.5155 | E25: =D26 -> 7258.51 | F25: =E26 -> 7045.2247 | G25: =F26 -> 7305.498 | H25: =G26 -> 8152.4131 | I25: =H26 -> 9695.6607 | J25: =I26 -> 11999.211 | ... M25: =L26 -> 24251.381
A26: Closing cash | B26: =IF(AND(ISNUMBER(B25),ISNUMBER(B24)),B25+B24,"Unknown") -> 8812.15 | C26: =IF(AND(ISNUMBER(C25),ISNUMBER(C24)),C25+C24,"Unknown") -> 7872.5155 | D26: =IF(AND(ISNUMBER(D25),ISNUMBER(D24)),D25+D24,"Unknown") -> 7258.51 | E26: =IF(AND(ISNUMBER(E25),ISNUMBER(E24)),E25+E24,"Unknown") -> 7045.2247 | F26: =IF(AND(ISNUMBER(F25),ISNUMBER(F24)),F25+F24,"Unknown") -> 7305.498 | G26: =IF(AND(ISNUMBER(G25),ISNUMBER(G24)),G25+G24,"Unknown") -> 8152.4131 | H26: =IF(AND(ISNUMBER(H25),ISNUMBER(H24)),H25+H24,"Unknown") -> 9695.6607 | I26: =IF(AND(ISNUMBER(I25),ISNUMBER(I24)),I25+I24,"Unknown") -> 11999.211 | ... M26: =IF(AND(ISNUMBER(M25),ISNUMBER(M24)),M25+M24,"Unknown") -> 30405.41
A27: Negative cash flag | B27: =IF(ISNUMBER(B26),IF(B26<0,1,0),"Unknown") -> 0 | C27: =IF(ISNUMBER(C26),IF(C26<0,1,0),"Unknown") -> 0 | D27: =IF(ISNUMBER(D26),IF(D26<0,1,0),"Unknown") -> 0 | E27: =IF(ISNUMBER(E26),IF(E26<0,1,0),"Unknown") -> 0 | F27: =IF(ISNUMBER(F26),IF(F26<0,1,0),"Unknown") -> 0 | G27: =IF(ISNUMBER(G26),IF(G26<0,1,0),"Unknown") -> 0 | H27: =IF(ISNUMBER(H26),IF(H26<0,1,0),"Unknown") -> 0 | I27: =IF(ISNUMBER(I26),IF(I26<0,1,0),"Unknown") -> 0 | ... M27: =IF(ISNUMBER(M26),IF(M26<0,1,0),"Unknown") -> 0
A28: Unfunded deficit | B28: =IF(ISNUMBER(B26),MAX(0,-B26),"Unknown") -> 0 | C28: =IF(ISNUMBER(C26),MAX(0,-C26),"Unknown") -> 0 | D28: =IF(ISNUMBER(D26),MAX(0,-D26),"Unknown") -> 0 | E28: =IF(ISNUMBER(E26),MAX(0,-E26),"Unknown") -> 0 | F28: =IF(ISNUMBER(F26),MAX(0,-F26),"Unknown") -> 0 | G28: =IF(ISNUMBER(G26),MAX(0,-G26),"Unknown") -> 0 | H28: =IF(ISNUMBER(H26),MAX(0,-H26),"Unknown") -> 0 | I28: =IF(ISNUMBER(I26),MAX(0,-I26),"Unknown") -> 0 | ... M28: =IF(ISNUMBER(M26),MAX(0,-M26),"Unknown") -> 0

Sheet Downside forecast
A1: Downside forecast — all assumptions, USD
B4: 46327 | C4: 46357 | D4: 46388 | E4: 46419 | F4: 46447 | G4: 46478 | H4: 46508 | I4: 46539 | J4: 46569 | K4: 46600 | L4: 46631 | M4: 46661
A5: Opening teams | B5: =Assumptions!$C$8 -> 0 | C5: =B8 -> 2 | D5: =C8 -> 3.84 | E5: =D8 -> 6.5328 | F5: =E8 -> 9.010176 | G5: =F8 -> 12.289362 | H5: =G8 -> 15.306213 | I5: =H8 -> 19.081716 | J5: =I8 -> 22.555179 | ... M5: =L8 -> 35.161847
A6: New teams | B6: =Assumptions!C26 -> 2 | C6: =Assumptions!C27 -> 2 | D6: =Assumptions!C28 -> 3 | E6: =Assumptions!C29 -> 3 | F6: =Assumptions!C30 -> 4 | G6: =Assumptions!C31 -> 4 | H6: =Assumptions!C32 -> 5 | I6: =Assumptions!C33 -> 5 | J6: =Assumptions!C34 -> 6 | K6: =Assumptions!C35 -> 6 | L6: =Assumptions!C36 -> 7 | M6: =Assumptions!C37 -> 7
A7: Churned teams | B7: =B5*Assumptions!$C$11 -> 0 | C7: =C5*Assumptions!$C$11 -> 0.16 | D7: =D5*Assumptions!$C$11 -> 0.3072 | E7: =E5*Assumptions!$C$11 -> 0.522624 | F7: =F5*Assumptions!$C$11 -> 0.72081408 | G7: =G5*Assumptions!$C$11 -> 0.98314895 | H7: =H5*Assumptions!$C$11 -> 1.224497 | I7: =I5*Assumptions!$C$11 -> 1.5265373 | ... M7: =M5*Assumptions!$C$11 -> 2.8129478
A8: Closing teams | B8: =B5-B7+B6 -> 2 | C8: =C5-C7+C6 -> 3.84 | D8: =D5-D7+D6 -> 6.5328 | E8: =E5-E7+E6 -> 9.010176 | F8: =F5-F7+F6 -> 12.289362 | G8: =G5-G7+G6 -> 15.306213 | H8: =H5-H7+H6 -> 19.081716 | I8: =I5-I7+I6 -> 22.555179 | ... M8: =M5-M7+M6 -> 39.348899
A9: Investigations | B9: =B8*Assumptions!$C$10*Assumptions!$C$12 -> 200 | C9: =C8*Assumptions!$C$10*Assumptions!$C$12 -> 384 | D9: =D8*Assumptions!$C$10*Assumptions!$C$12 -> 653.28 | E9: =E8*Assumptions!$C$10*Assumptions!$C$12 -> 901.0176 | F9: =F8*Assumptions!$C$10*Assumptions!$C$12 -> 1228.9362 | G9: =G8*Assumptions!$C$10*Assumptions!$C$12 -> 1530.6213 | H9: =H8*Assumptions!$C$10*Assumptions!$C$12 -> 1908.1716 | I9: =I8*Assumptions!$C$10*Assumptions!$C$12 -> 2255.5179 | ... M9: =M8*Assumptions!$C$10*Assumptions!$C$12 -> 3934.8899
A10: Revenue | B10: =B8*Assumptions!$C$9 -> 98 | C10: =C8*Assumptions!$C$9 -> 188.16 | D10: =D8*Assumptions!$C$9 -> 320.1072 | E10: =E8*Assumptions!$C$9 -> 441.49862 | F10: =F8*Assumptions!$C$9 -> 602.17873 | G10: =G8*Assumptions!$C$9 -> 750.00444 | H10: =H8*Assumptions!$C$9 -> 935.00408 | I10: =I8*Assumptions!$C$9 -> 1105.2038 | ... M10: =M8*Assumptions!$C$9 -> 1928.0961
A11: Run cost per investigation | B11: =IF(Assumptions!$B$4="Planning",SUM(Assumptions!$C$13,Assumptions!$C$14,Assumptions!$C$15),'Assumptions vs actuals'!$B$7) -> 0.285 | C11: =IF(Assumptions!$B$4="Planning",SUM(Assumptions!$C$13,Assumptions!$C$14,Assumptions!$C$15),'Assumptions vs actuals'!$B$7) -> 0.285 | D11: =IF(Assumptions!$B$4="Planning",SUM(Assumptions!$C$13,Assumptions!$C$14,Assumptions!$C$15),'Assumptions vs actuals'!$B$7) -> 0.285 | E11: =IF(Assumptions!$B$4="Planning",SUM(Assumptions!$C$13,Assumptions!$C$14,Assumptions!$C$15),'Assumptions vs actuals'!$B$7) -> 0.285 | F11: =IF(Assumptions!$B$4="Planning",SUM(Assumptions!$C$13,Assumptions!$C$14,Assumptions!$C$15),'Assumptions vs actuals'!$B$7) -> 0.285 | G11: =IF(Assumptions!$B$4="Planning",SUM(Assumptions!$C$13,Assumptions!$C$14,Assumptions!$C$15),'Assumptions vs actuals'!$B$7) -> 0.285 | H11: =IF(Assumptions!$B$4="Planning",SUM(Assumptions!$C$13,Assumptions!$C$14,Assumptions!$C$15),'Assumptions vs actuals'!$B$7) -> 0.285 | I11: =IF(Assumptions!$B$4="Planning",SUM(Assumptions!$C$13,Assumptions!$C$14,Assumptions!$C$15),'Assumptions vs actuals'!$B$7) -> 0.285 | ... M11: =IF(Assumptions!$B$4="Planning",SUM(Assumptions!$C$13,Assumptions!$C$14,Assumptions!$C$15),'Assumptions vs actuals'!$B$7) -> 0.285
A12: Investigation variable cost | B12: =IF(ISNUMBER(B11),B9*B11,"Unknown") -> 57 | C12: =IF(ISNUMBER(C11),C9*C11,"Unknown") -> 109.44 | D12: =IF(ISNUMBER(D11),D9*D11,"Unknown") -> 186.1848 | E12: =IF(ISNUMBER(E11),E9*E11,"Unknown") -> 256.79002 | F12: =IF(ISNUMBER(F11),F9*F11,"Unknown") -> 350.24681 | G12: =IF(ISNUMBER(G11),G9*G11,"Unknown") -> 436.22707 | H12: =IF(ISNUMBER(H11),H9*H11,"Unknown") -> 543.8289 | I12: =IF(ISNUMBER(I11),I9*I11,"Unknown") -> 642.82259 | ... M12: =IF(ISNUMBER(M11),M9*M11,"Unknown") -> 1121.4436
A13: Payment fees | B13: =B10*Assumptions!$C$16+B8*Assumptions!$C$17 -> 3.54 | C13: =C10*Assumptions!$C$16+C8*Assumptions!$C$17 -> 6.7968 | D13: =D10*Assumptions!$C$16+D8*Assumptions!$C$17 -> 11.563056 | E13: =E10*Assumptions!$C$16+E8*Assumptions!$C$17 -> 15.948012 | F13: =F10*Assumptions!$C$16+F8*Assumptions!$C$17 -> 21.752171 | G13: =G10*Assumptions!$C$16+G8*Assumptions!$C$17 -> 27.091997 | H13: =H10*Assumptions!$C$16+H8*Assumptions!$C$17 -> 33.774637 | I13: =I10*Assumptions!$C$16+I8*Assumptions!$C$17 -> 39.922666 | ... M13: =M10*Assumptions!$C$16+M8*Assumptions!$C$17 -> 69.647552
A14: Total variable cost | B14: =IF(ISNUMBER(B12),B12+B13,"Unknown") -> 60.54 | C14: =IF(ISNUMBER(C12),C12+C13,"Unknown") -> 116.2368 | D14: =IF(ISNUMBER(D12),D12+D13,"Unknown") -> 197.74786 | E14: =IF(ISNUMBER(E12),E12+E13,"Unknown") -> 272.73803 | F14: =IF(ISNUMBER(F12),F12+F13,"Unknown") -> 371.99899 | G14: =IF(ISNUMBER(G12),G12+G13,"Unknown") -> 463.31907 | H14: =IF(ISNUMBER(H12),H12+H13,"Unknown") -> 577.60354 | I14: =IF(ISNUMBER(I12),I12+I13,"Unknown") -> 682.74526 | ... M14: =IF(ISNUMBER(M12),M12+M13,"Unknown") -> 1191.0912
A15: Contribution before hosting | B15: =IF(ISNUMBER(B14),B10-B14,"Unknown") -> 37.46 | C15: =IF(ISNUMBER(C14),C10-C14,"Unknown") -> 71.9232 | D15: =IF(ISNUMBER(D14),D10-D14,"Unknown") -> 122.35934 | E15: =IF(ISNUMBER(E14),E10-E14,"Unknown") -> 168.7606 | F15: =IF(ISNUMBER(F14),F10-F14,"Unknown") -> 230.17975 | G15: =IF(ISNUMBER(G14),G10-G14,"Unknown") -> 286.68537 | H15: =IF(ISNUMBER(H14),H10-H14,"Unknown") -> 357.40054 | I15: =IF(ISNUMBER(I14),I10-I14,"Unknown") -> 422.4585 | ... M15: =IF(ISNUMBER(M14),M10-M14,"Unknown") -> 737.00488
A16: Contribution margin before hosting | B16: =IFERROR(B15/B10,"Unknown") -> 0.3822449 | C16: =IFERROR(C15/C10,"Unknown") -> 0.3822449 | D16: =IFERROR(D15/D10,"Unknown") -> 0.3822449 | E16: =IFERROR(E15/E10,"Unknown") -> 0.3822449 | F16: =IFERROR(F15/F10,"Unknown") -> 0.3822449 | G16: =IFERROR(G15/G10,"Unknown") -> 0.3822449 | H16: =IFERROR(H15/H10,"Unknown") -> 0.3822449 | I16: =IFERROR(I15/I10,"Unknown") -> 0.3822449 | ... M16: =IFERROR(M15/M10,"Unknown") -> 0.3822449
A17: Fixed hosting | B17: =Assumptions!$C$18 -> 100 | C17: =Assumptions!$C$18 -> 100 | D17: =Assumptions!$C$18 -> 100 | E17: =Assumptions!$C$18 -> 100 | F17: =Assumptions!$C$18 -> 100 | G17: =Assumptions!$C$18 -> 100 | H17: =Assumptions!$C$18 -> 100 | I17: =Assumptions!$C$18 -> 100 | ... M17: =Assumptions!$C$18 -> 100
A18: Gross profit | B18: =IF(ISNUMBER(B15),B15-B17,"Unknown") -> -62.54 | C18: =IF(ISNUMBER(C15),C15-C17,"Unknown") -> -28.0768 | D18: =IF(ISNUMBER(D15),D15-D17,"Unknown") -> 22.359344 | E18: =IF(ISNUMBER(E15),E15-E17,"Unknown") -> 68.760596 | F18: =IF(ISNUMBER(F15),F15-F17,"Unknown") -> 130.17975 | G18: =IF(ISNUMBER(G15),G15-G17,"Unknown") -> 186.68537 | H18: =IF(ISNUMBER(H15),H15-H17,"Unknown") -> 257.40054 | I18: =IF(ISNUMBER(I15),I15-I17,"Unknown") -> 322.4585 | ... M18: =IF(ISNUMBER(M15),M15-M17,"Unknown") -> 637.00488
A19: Gross margin | B19: =IFERROR(B18/B10,"Unknown") -> -0.63816327 | C19: =IFERROR(C18/C10,"Unknown") -> -0.14921769 | D19: =IFERROR(D18/D10,"Unknown") -> 0.06984955 | E19: =IFERROR(E18/E10,"Unknown") -> 0.15574363 | F19: =IFERROR(F18/F10,"Unknown") -> 0.21618125 | G19: =IFERROR(G18/G10,"Unknown") -> 0.24891235 | H19: =IFERROR(H18/H10,"Unknown") -> 0.27529349 | I19: =IFERROR(I18/I10,"Unknown") -> 0.29176384 | ... M19: =IFERROR(M18/M10,"Unknown") -> 0.33038026
A20: Founder/contractor cash pay | B20: =Assumptions!$C$19 -> 2000 | C20: =Assumptions!$C$19 -> 2000 | D20: =Assumptions!$C$19 -> 2000 | E20: =Assumptions!$C$19 -> 2000 | F20: =Assumptions!$C$19 -> 2000 | G20: =Assumptions!$C$19 -> 2000 | H20: =Assumptions!$C$19 -> 2000 | I20: =Assumptions!$C$19 -> 2000 | ... M20: =Assumptions!$C$19 -> 2000
A21: Marketing | B21: =Assumptions!$C$20 -> 300 | C21: =Assumptions!$C$20 -> 300 | D21: =Assumptions!$C$20 -> 300 | E21: =Assumptions!$C$20 -> 300 | F21: =Assumptions!$C$20 -> 300 | G21: =Assumptions!$C$20 -> 300 | H21: =Assumptions!$C$20 -> 300 | I21: =Assumptions!$C$20 -> 300 | ... M21: =Assumptions!$C$20 -> 300
A22: Other operating spend | B22: =Assumptions!$C$21 -> 200 | C22: =Assumptions!$C$21 -> 200 | D22: =Assumptions!$C$21 -> 200 | E22: =Assumptions!$C$21 -> 200 | F22: =Assumptions!$C$21 -> 200 | G22: =Assumptions!$C$21 -> 200 | H22: =Assumptions!$C$21 -> 200 | I22: =Assumptions!$C$21 -> 200 | ... M22: =Assumptions!$C$21 -> 200
A23: Total operating spend | B23: =SUM(B20:B22) -> 2500 | C23: =SUM(C20:C22) -> 2500 | D23: =SUM(D20:D22) -> 2500 | E23: =SUM(E20:E22) -> 2500 | F23: =SUM(F20:F22) -> 2500 | G23: =SUM(G20:G22) -> 2500 | H23: =SUM(H20:H22) -> 2500 | I23: =SUM(I20:I22) -> 2500 | ... M23: =SUM(M20:M22) -> 2500
A24: Operating cash flow | B24: =IF(ISNUMBER(B18),B18-B23,"Unknown") -> -2562.54 | C24: =IF(ISNUMBER(C18),C18-C23,"Unknown") -> -2528.0768 | D24: =IF(ISNUMBER(D18),D18-D23,"Unknown") -> -2477.6407 | E24: =IF(ISNUMBER(E18),E18-E23,"Unknown") -> -2431.2394 | F24: =IF(ISNUMBER(F18),F18-F23,"Unknown") -> -2369.8203 | G24: =IF(ISNUMBER(G18),G18-G23,"Unknown") -> -2313.3146 | H24: =IF(ISNUMBER(H18),H18-H23,"Unknown") -> -2242.5995 | I24: =IF(ISNUMBER(I18),I18-I23,"Unknown") -> -2177.5415 | ... M24: =IF(ISNUMBER(M18),M18-M23,"Unknown") -> -1862.9951
A25: Opening cash | B25: =Assumptions!$C$7 -> 10000 | C25: =B26 -> 7437.46 | D25: =C26 -> 4909.3832 | E25: =D26 -> 2431.7425 | F25: =E26 -> 0.50314048 | G25: =F26 -> -2369.3171 | H25: =G26 -> -4682.6317 | I25: =H26 -> -6925.2312 | J25: =I26 -> -9102.7727 | ... M25: =L26 -> -15169.811
A26: Closing cash | B26: =IF(AND(ISNUMBER(B25),ISNUMBER(B24)),B25+B24,"Unknown") -> 7437.46 | C26: =IF(AND(ISNUMBER(C25),ISNUMBER(C24)),C25+C24,"Unknown") -> 4909.3832 | D26: =IF(AND(ISNUMBER(D25),ISNUMBER(D24)),D25+D24,"Unknown") -> 2431.7425 | E26: =IF(AND(ISNUMBER(E25),ISNUMBER(E24)),E25+E24,"Unknown") -> 0.50314048 | F26: =IF(AND(ISNUMBER(F25),ISNUMBER(F24)),F25+F24,"Unknown") -> -2369.3171 | G26: =IF(AND(ISNUMBER(G25),ISNUMBER(G24)),G25+G24,"Unknown") -> -4682.6317 | H26: =IF(AND(ISNUMBER(H25),ISNUMBER(H24)),H25+H24,"Unknown") -> -6925.2312 | I26: =IF(AND(ISNUMBER(I25),ISNUMBER(I24)),I25+I24,"Unknown") -> -9102.7727 | ... M26: =IF(AND(ISNUMBER(M25),ISNUMBER(M24)),M25+M24,"Unknown") -> -17032.806
A27: Negative cash flag | B27: =IF(ISNUMBER(B26),IF(B26<0,1,0),"Unknown") -> 0 | C27: =IF(ISNUMBER(C26),IF(C26<0,1,0),"Unknown") -> 0 | D27: =IF(ISNUMBER(D26),IF(D26<0,1,0),"Unknown") -> 0 | E27: =IF(ISNUMBER(E26),IF(E26<0,1,0),"Unknown") -> 0 | F27: =IF(ISNUMBER(F26),IF(F26<0,1,0),"Unknown") -> 1 | G27: =IF(ISNUMBER(G26),IF(G26<0,1,0),"Unknown") -> 1 | H27: =IF(ISNUMBER(H26),IF(H26<0,1,0),"Unknown") -> 1 | I27: =IF(ISNUMBER(I26),IF(I26<0,1,0),"Unknown") -> 1 | ... M27: =IF(ISNUMBER(M26),IF(M26<0,1,0),"Unknown") -> 1
A28: Unfunded deficit | B28: =IF(ISNUMBER(B26),MAX(0,-B26),"Unknown") -> 0 | C28: =IF(ISNUMBER(C26),MAX(0,-C26),"Unknown") -> 0 | D28: =IF(ISNUMBER(D26),MAX(0,-D26),"Unknown") -> 0 | E28: =IF(ISNUMBER(E26),MAX(0,-E26),"Unknown") -> 0 | F28: =IF(ISNUMBER(F26),MAX(0,-F26),"Unknown") -> 2369.3171 | G28: =IF(ISNUMBER(G26),MAX(0,-G26),"Unknown") -> 4682.6317 | H28: =IF(ISNUMBER(H26),MAX(0,-H26),"Unknown") -> 6925.2312 | I28: =IF(ISNUMBER(I26),MAX(0,-I26),"Unknown") -> 9102.7727 | ... M28: =IF(ISNUMBER(M26),MAX(0,-M26),"Unknown") -> 17032.806

Sheet Credits
A1: Credits are separate from commercial cost and are not forecast financing
A2: Credit ID | B2: Date | C2: Amount USD | D2: Provider | E2: Evidence

Sheet Read me
A1: BugReplay: editable assumption-led model, rebuilt alongside the saved cfo.ai workspace model.
A2: Prototype: vague browser complaint to independently verified Playwright reproduction; initially cart preservation in one controlled shop.
A3: Horizon: November 2026–October 2027; USD; zero opening teams; $10,000 assumed opening cash.
A4: Churn applies to opening teams. New teams arrive at start of month. Bill closing teams for full month. Fractional teams are expected-value forecasts.
A5: Revenue is collected same month. Costs include failed/cancelled investigations. Payment fees are 3% revenue + $0.30 per billed team.
A6: Contribution excludes hosting; gross profit deducts hosting. Cash deducts founder/contractor, marketing and other cash operating spend.
A7: No tax, debt, capex or working-capital timing is modeled. No borrowing assumed. First negative closing cash flags financing need.
A8: Actual register and expected paid-attempt count remain empty. Actual cost is Unknown; explicit zero requires verified evidence. Credits never net against commercial cost.
A9: Planning is selected. Measured mode only uses a complete, validated all-in cost ledger; missing costs leave cash Unknown, never zero.
A10: Case selector: Assumptions!B3. Cost-basis selector: Assumptions!B4. Blue text marks editable inputs.
A11: This workbook is an editable snapshot, not a live connection back to cfo.ai. New workspace edits require a new export.
A12: Source inputs: https://github.com/prokiller67-crypto/bugreplay/tree/8f378b2c08add81e3901df6475b43d239fe0b89c/docs/evidence/finance
... A15: Native comparison and this workbook reproduce all 12 original published monthly results; no adjustment is used. The workbook preserves Planning selection.
